{"ref":"55ea8f60-86e3-4a27-b0e1-73ab0f41a03c","syncData":{"version":2,"machineId":"8cc6be6b-3ef5-4051-ac1b-e9e34c90daa2","content":"{\"settings\":\"{\\r\\n    \\\"git.terminalGitEditor\\\": true,\\r\\n    \\\"terminal.integrated.defaultProfile.windows\\\": \\\"PowerShell\\\",\\r\\n    \\\"settingsSync.ignoredSettings\\\": [],\\r\\n    \\\"settingsSync.ignoredExtensions\\\": [\\r\\n        \\\"vscode.theme-monokai\\\"\\r\\n    ],\\r\\n    \\\"liveServer.settings.donotVerifyTags\\\": true,\\r\\n    \\\"liveServer.settings.donotShowInfoMsg\\\": true,\\r\\n    \\\"[html]\\\": {\\r\\n        \\\"editor.defaultFormatter\\\": \\\"vscode.html-language-features\\\"\\r\\n    },\\r\\n    \\\"[css]\\\": {\\r\\n        \\\"editor.defaultFormatter\\\": \\\"esbenp.prettier-vscode\\\"\\r\\n    },\\r\\n    \\\"mssql.enableRichExperiences\\\": true,\\r\\n    \\\"workbench.editorAssociations\\\": {\\r\\n        \\\"*.copilotmd\\\": \\\"vscode.markdown.preview.editor\\\",\\r\\n        \\\"{hexdiff}:/**/*.*\\\": \\\"hexEditor.hexedit\\\",\\r\\n        \\\"*.pickle\\\": \\\"default\\\",\\r\\n        \\\"*.bin\\\": \\\"default\\\",\\r\\n        \\\"*.db\\\": \\\"hexEditor.hexedit\\\"\\r\\n    },\\r\\n    \\\"workbench.iconTheme\\\": \\\"material-icon-theme\\\",\\r\\n    \\\"[ignore]\\\": {},\\r\\n    \\\"workbench.colorTheme\\\": \\\"Bearded Theme Monokai Metallian\\\",\\r\\n    \\\"git.openRepositoryInParentFolders\\\": \\\"never\\\",\\r\\n    \\\"database-client.autoSync\\\": true,\\r\\n    \\\"git.confirmSync\\\": false,\\r\\n    \\\"git.autofetch\\\": true,\\r\\n    \\\"[json]\\\": {\\r\\n        \\\"editor.defaultFormatter\\\": \\\"esbenp.prettier-vscode\\\"\\r\\n    },\\r\\n    \\\"[python]\\\": {\\r\\n        \\\"diffEditor.ignoreTrimWhitespace\\\": false,\\r\\n        \\\"editor.defaultColorDecorators\\\": \\\"never\\\",\\r\\n        \\\"gitlens.codeLens.symbolScopes\\\": [\\r\\n            \\\"!Module\\\"\\r\\n        ],\\r\\n        \\\"editor.formatOnType\\\": true,\\r\\n        \\\"editor.wordBasedSuggestions\\\": \\\"off\\\"\\r\\n    },\\r\\n    \\\"files.associations\\\": {\\r\\n        \\\"*.dbclient-js\\\": \\\"javascript\\\",\\r\\n        \\\"*.py\\\": \\\"python\\\",\\r\\n        \\\"*.rmd\\\": \\\"markdown\\\"\\r\\n    },\\r\\n    \\\"editor.cursorBlinking\\\": \\\"expand\\\",\\r\\n    \\\"editor.cursorSmoothCaretAnimation\\\": \\\"on\\\",\\r\\n    \\\"sqlite3-editor.ui.minimizePanel\\\": true,\\r\\n    \\\"editor.unicodeHighlight.invisibleCharacters\\\": false,\\r\\n    \\\"editor.unicodeHighlight.ambiguousCharacters\\\": false,\\r\\n    \\\"mssql.connectionGroups\\\": [\\r\\n        {\\r\\n            \\\"name\\\": \\\"ROOT\\\",\\r\\n            \\\"id\\\": \\\"84E57453-4550-4D28-95B8-EE2DEAAAD6AA\\\"\\r\\n        }\\r\\n    ],\\r\\n    \\\"mssql.connections\\\": [],\\r\\n    \\\"terminal.integrated.suggest.enabled\\\": true,\\r\\n    \\\"database-client.highlightSQLBlock\\\": true,\\r\\n    \\\"database-client.capitalizeKeywordsWhenFormatting\\\": true,\\r\\n    \\\"github.copilot.advanced\\\": {\\r\\n        \\\"authProvider\\\": \\\"github-enterprise\\\"\\r\\n    },\\r\\n    \\\"security.workspace.trust.untrustedFiles\\\": \\\"open\\\",\\r\\n    \\\"python.analysis.diagnosticSeverityOverrides\\\": {},\\r\\n    \\\"terminal.integrated.fontFamily\\\": \\\"MesloLGS NF\\\",\\r\\n    \\\"terminal.integrated.fontLigatures.enabled\\\": true,\\r\\n    \\\"pgsql.serverGroups\\\": [\\r\\n        {\\r\\n            \\\"name\\\": \\\"Servers\\\",\\r\\n            \\\"id\\\": \\\"CB29AECF-F62F-40D9-9893-4F9DAE62FAA7\\\",\\r\\n            \\\"isDefault\\\": true\\r\\n        }\\r\\n    ],\\r\\n    \\\"pgsql.connections\\\": [\\r\\n        {\\r\\n            \\\"id\\\": \\\"4A726322-0CAB-41DB-B73A-B6D7332D3C3B\\\",\\r\\n            \\\"groupId\\\": \\\"CB29AECF-F62F-40D9-9893-4F9DAE62FAA7\\\",\\r\\n            \\\"authenticationType\\\": \\\"SqlLogin\\\",\\r\\n            \\\"connectTimeout\\\": 15,\\r\\n            \\\"applicationName\\\": \\\"vscode-pgsql\\\",\\r\\n            \\\"clientEncoding\\\": \\\"utf8\\\",\\r\\n            \\\"sslmode\\\": \\\"prefer\\\",\\r\\n            \\\"password\\\": \\\"\\\",\\r\\n            \\\"user\\\": \\\"freeaiasist\\\",\\r\\n            \\\"server\\\": \\\"localhost\\\",\\r\\n            \\\"database\\\": \\\"freeaiasistant\\\",\\r\\n            \\\"profileName\\\": \\\"freeaiasistant\\\",\\r\\n            \\\"port\\\": \\\"5532\\\",\\r\\n            \\\"expiresOn\\\": 0\\r\\n        }\\r\\n    ],\\r\\n    \\\"liveServer.settings.port\\\": 5500,\\r\\n    \\\"workbench.colorCustomizations\\\": {\\r\\n        },\\r\\n    \\\"window.titleBarStyle\\\": \\\"custom\\\",\\r\\n    \\\"[r]\\\": {\\r\\n        \\\"editor.wordSeparators\\\": \\\"`~!@#$%^&*()-=+[{]}\\\\\\\\|;:'\\\\\\\",<>/\\\"\\r\\n    },\\r\\n    \\\"r.rterm.linux\\\": \\\"/home/alexey/.local/bin/radian\\\",\\r\\n    \\\"r.rpath.linux\\\": \\\"/home/alexey/.local/bin/radian\\\",\\r\\n    \\\"editor.fontFamily\\\": \\\"'Dank Mono', 'Droid Sans Mono', 'monospace', monospace\\\",\\r\\n    \\\"editor.fontSize\\\": 15,\\r\\n}\"}"}}